flexivddk/__init__.py
flexivddk/flexivddk.cp38-win_amd64.pyd
flexivddk-1.2.0.dist-info/LICENSE
flexivddk-1.2.0.dist-info/METADATA
flexivddk-1.2.0.dist-info/WHEEL
flexivddk-1.2.0.dist-info/top_level.txt
flexivddk-1.2.0.dist-info/RECORD
