Metadata-Version: 2.1
Name: flexivddk
Version: 1.2.0
Summary: Flexiv DDK Python library
Author: Flexiv Ltd
Author-email: business@flexiv.com
License: Apache-2.0
Requires-Python: >=3.8
License-File: LICENSE
